poseidon_api/__init__.py
poseidon_api/api.py
poseidon_api/data.py
poseidon_api/routes.py
poseidon_api-0.18.2.dist-info/entry_points.txt
poseidon_api-0.18.2.dist-info/WHEEL
poseidon_api-0.18.2.dist-info/METADATA
poseidon_api-0.18.2.dist-info/RECORD
