Metadata-Version: 2.1
Name: poseidon-api
Version: 0.18.2
Summary: RESTful API for querying Poseidon
License: Apache-2.0
Author: cglewis
Author-email: clewis@iqt.org
Requires-Python: >=3.8,<3.11
Classifier: License :: OSI Approved :: Apache Software License
Classifier: Programming Language :: Python :: 3
Classifier: Programming Language :: Python :: 3.8
Classifier: Programming Language :: Python :: 3.9
Classifier: Programming Language :: Python :: 3.10
Requires-Dist: bjoern (==3.2.2)
Requires-Dist: falcon (==3.1.0)
Requires-Dist: falcon-cors (==1.1.7)
Requires-Dist: httpx (==0.23.0)
Requires-Dist: natural (==0.2.0)
Requires-Dist: poseidon-core (==0.18.1)
Project-URL: homepage, https://github.com/IQTLabs/poseidon
